web_scraping_mcp_server/__init__.py
web_scraping_mcp_server/extractors.py
web_scraping_mcp_server/logconfig.py
web_scraping_mcp_server/main.py
web_scraping_mcp_server/scraper.py
web_scraping_mcp_server/scrapingbee/__init__.py
web_scraping_mcp_server/scrapingbee/client.py
web_scraping_mcp_server/scrapingbee/exceptions.py
web_scraping_mcp_server/server.py
web_scraping_mcp_server/settings.py
web_scraping_mcp_server/utils.py
web_scraping_mcp_server-0.2.1.dist-info/WHEEL
web_scraping_mcp_server-0.2.1.dist-info/entry_points.txt
web_scraping_mcp_server-0.2.1.dist-info/METADATA
web_scraping_mcp_server-0.2.1.dist-info/RECORD
