Metadata-Version: 2.3
Name: web-scraping-mcp-server
Version: 0.2.1
Summary: A web scraping service with HTML extraction tools using ScrapingBee API and FastMCP
Author: Joe Joiner
Author-email: Joe Joiner <2454320+joejoinerr@users.noreply.github.com>
Requires-Dist: beautifulsoup4>=4.13.4
Requires-Dist: fastmcp>=2.10.6
Requires-Dist: httpx[http2]>=0.28.1
Requires-Dist: loguru>=0.7.3
Requires-Dist: lxml>=6.0.0
Requires-Dist: pydantic-settings>=2.10.1
Requires-Dist: tenacity>=9.1.2
Requires-Python: >=3.12
